ohtell/__init__.py
ohtell/config.py
ohtell/interceptors.py
ohtell/metrics.py
ohtell/providers.py
ohtell/tracer.py
ohtell-0.2.24.dist-info/licenses/LICENSE
ohtell-0.2.24.dist-info/METADATA
ohtell-0.2.24.dist-info/WHEEL
ohtell-0.2.24.dist-info/top_level.txt
ohtell-0.2.24.dist-info/RECORD
